{"ongoing_trials": {}, "hyperparameters": {"space": [{"class_name": "Int", "config": {"name": "units", "default": null, "conditions": [], "min_value": 10, "max_value": 25, "step": 2, "sampling": null}}, {"class_name": "Choice", "config": {"name": "learning_rate", "default": 0.01, "conditions": [], "values": [0.01], "ordered": true}}], "values": {"units": 10, "learning_rate": 0.01}}, "seed": 9088, "seed_state": 9106, "tried_so_far": ["ece4011bd65d84195617e9dfaed5638d", "01925180f4593b5e1a1e7c72e7581fc8", "d465d6e6e96e09981c93e336cad6c8a5", "4507ce701b6aa4c97b1c70dbc01e1015", "2c23992272715a548676a374e6708d0d", "e5de615b6581f84191c91cf0a31b0d02"]}